funmodel/__init__.py
funmodel/dwpose/__init__.py
funmodel/dwpose/predictor.py
funmodel/dwpose/core/__init__.py
funmodel/dwpose/core/onnxdet.py
funmodel/dwpose/core/onnxpose.py
funmodel/dwpose/core/util.py
funmodel/dwpose/core/wholebody.py
funmodel_dwpose-0.0.11.dist-info/LICENSE
funmodel_dwpose-0.0.11.dist-info/METADATA
funmodel_dwpose-0.0.11.dist-info/WHEEL
funmodel_dwpose-0.0.11.dist-info/top_level.txt
funmodel_dwpose-0.0.11.dist-info/RECORD
