Metadata-Version: 2.1
Name: funmodel-dwpose
Version: 0.0.11
Summary: funmodel-dwpose
Home-page: https://github.com/farfarfun/funmodel-dwpose
Author: bingtao
Author-email: 1007530194@qq.com
License-File: LICENSE
Requires-Dist: funmodel
